[
  {
    "Todo": "a",
    "LimitDay": "2025-04-07T11:11:53.180641+09:00",
    "IsCompleted": false
  },
  {
    "Todo": "f",
    "LimitDay": "2025-04-07T11:11:53.180641+09:00",
    "IsCompleted": true
  },
  {
    "Todo": "g",
    "LimitDay": "2025-04-07T11:11:53.180641+09:00",
    "IsCompleted": false
  },
  {
    "Todo": "h",
    "LimitDay": "2025-04-30T11:11:53",
    "IsCompleted": true
  },
  {
    "Todo": "j",
    "LimitDay": "2025-04-30T11:11:53",
    "IsCompleted": false
  },
  {
    "Todo": "t",
    "LimitDay": "2025-04-30T11:11:53",
    "IsCompleted": false
  }
]